bt_ddos_shield/__init__.py
bt_ddos_shield/address_manager.py
bt_ddos_shield/blockchain_manager.py
bt_ddos_shield/certificate_manager.py
bt_ddos_shield/client.py
bt_ddos_shield/encryption_manager.py
bt_ddos_shield/event_processor.py
bt_ddos_shield/manifest_manager.py
bt_ddos_shield/miner_shield.py
bt_ddos_shield/shield_metagraph.py
bt_ddos_shield/state_manager.py
bt_ddos_shield/utils.py
bt_ddos_shield/validators_manager.py
bt_ddos_shield/turbobt/__init__.py
bt_ddos_shield/turbobt/blockchain_manager.py
bt_ddos_shield/turbobt/shielded_bittensor.py
bt_ddos_shield_client-0.3.4.dist-info/licenses/LICENSE
bt_ddos_shield_client-0.3.4.dist-info/METADATA
bt_ddos_shield_client-0.3.4.dist-info/WHEEL
bt_ddos_shield_client-0.3.4.dist-info/top_level.txt
bt_ddos_shield_client-0.3.4.dist-info/RECORD
