Metadata-Version: 2.4
Name: bt-ddos-shield-client
Version: 0.3.4
Requires-Python: >=3.11.0
License-File: LICENSE
Requires-Dist: bittensor~=9.9.0
Requires-Dist: boto3~=1.36.21
Requires-Dist: cryptography~=43.0.3
Requires-Dist: eciespy~=0.4.6
Requires-Dist: pydantic~=2.10.6
Requires-Dist: pydantic-settings~=2.7.1
Requires-Dist: python-dotenv~=1.0.1
Requires-Dist: route53~=1.0.1
Requires-Dist: sqlalchemy~=2.0.36
Provides-Extra: turbobt
Requires-Dist: turbobt~=0.3.1; extra == "turbobt"
Dynamic: license-file
